tgcrypto.cpython-312-i386-linux-gnu.so
tgcryptos-0.0.6.dist-info/METADATA
tgcryptos-0.0.6.dist-info/WHEEL
tgcryptos-0.0.6.dist-info/top_level.txt
tgcryptos-0.0.6.dist-info/RECORD
