Metadata-Version: 2.4
Name: TgCryptos
Version: 0.0.6
Summary: Fast and Portable Cryptography Extension Library for Pyrofork
Home-page: https://github.com/Clinton-Abraham
Author: Clinton-Abraham
Author-email: clintonabrahamc@gmail.com
License: LGPLv3+
Project-URL: Source, https://github.com/Clinton-Abraham
Project-URL: Community, https://telegram.me/sources_codes
Project-URL: Documentation, https://telegram.me/Clinton_Abraham
Keywords: pyrogram pyrofork telegram
Classifier: Operating System :: OS Independent
Classifier: Programming Language :: C
Classifier: Programming Language :: Python :: 3.10
Classifier: Programming Language :: Python :: 3.11
Classifier: Programming Language :: Python :: 3.12
Classifier: Programming Language :: Python :: 3.13
Classifier: Programming Language :: Python :: 3.14
Classifier: Programming Language :: Python :: Implementation
Classifier: Programming Language :: Python :: Implementation :: PyPy
Classifier: Programming Language :: Python :: Implementation :: CPython
Classifier: License :: OSI Approved :: GNU Lesser General Public License v3 or later (LGPLv3+)
Requires-Python: ~=3.10
Dynamic: author
Dynamic: author-email
Dynamic: classifier
Dynamic: description
Dynamic: description-content-type
Dynamic: home-page
Dynamic: keywords
Dynamic: license
Dynamic: project-url
Dynamic: requires-python
Dynamic: summary
